{
  "id": "break",
  "version": "1.0-beta.1",
  "title": "BREAK!!",
  "url": "https://github.com/Anyndol/FoundryVTT-Break",
  "manifest": "https://github.com/anyndelworks/FoundryVTT-Break/releases/download/v1.0-beta.1/system.json",
  "download": "https://github.com/anyndelworks/FoundryVTT-Break/releases/download/v1.0-beta.1/v1.0-beta.1.zip",
  "description": "A BREAK!! TTRPG game system",
  "license": "LICENSE.txt",
  "authors": [
    {
      "name": "Anyndol"
    },
    {
      "name": "Valkyrie"
    },
    {
      "name": "Nicolasra"
    }
  ],
  "esmodules": ["break.js"],
  "styles": ["styles/break.css"],
  "languages": [
    {
      "lang": "en",
      "name": "English",
      "path": "lang/en.json"
    },
    {
      "lang": "es",
      "name": "Español",
      "path": "lang/es.json"
    }
  ],
  "documentTypes": {
    "Actor": {
      "character": {
        "htmlFields": ["biography", "notes"]
      }
    }
  },
  "compatibility": {
    "minimum": "13",
    "verified": "13"
  },
  "grid": {
    "distance": 1,
    "units": "area"
  },
  "primaryTokenAttribute": "hearts",
  "secondaryTokenAttribute": "power"
}